odoo/addons/account_partner_required/README.rst
odoo/addons/account_partner_required/__init__.py
odoo/addons/account_partner_required/__manifest__.py
odoo/addons/account_partner_required/i18n/account_partner_required.pot
odoo/addons/account_partner_required/i18n/ar.po
odoo/addons/account_partner_required/i18n/bs.po
odoo/addons/account_partner_required/i18n/cs.po
odoo/addons/account_partner_required/i18n/de.po
odoo/addons/account_partner_required/i18n/en_GB.po
odoo/addons/account_partner_required/i18n/es.po
odoo/addons/account_partner_required/i18n/es_CR.po
odoo/addons/account_partner_required/i18n/es_EC.po
odoo/addons/account_partner_required/i18n/es_MX.po
odoo/addons/account_partner_required/i18n/fr.po
odoo/addons/account_partner_required/i18n/hr.po
odoo/addons/account_partner_required/i18n/hu.po
odoo/addons/account_partner_required/i18n/it.po
odoo/addons/account_partner_required/i18n/ja.po
odoo/addons/account_partner_required/i18n/lt.po
odoo/addons/account_partner_required/i18n/mk.po
odoo/addons/account_partner_required/i18n/mn.po
odoo/addons/account_partner_required/i18n/nb.po
odoo/addons/account_partner_required/i18n/nl.po
odoo/addons/account_partner_required/i18n/nl_BE.po
odoo/addons/account_partner_required/i18n/nl_NL.po
odoo/addons/account_partner_required/i18n/pt.po
odoo/addons/account_partner_required/i18n/pt_BR.po
odoo/addons/account_partner_required/i18n/ro.po
odoo/addons/account_partner_required/i18n/ru.po
odoo/addons/account_partner_required/i18n/sl.po
odoo/addons/account_partner_required/i18n/sv.po
odoo/addons/account_partner_required/i18n/tr.po
odoo/addons/account_partner_required/i18n/tr_TR.po
odoo/addons/account_partner_required/i18n/zh_CN.po
odoo/addons/account_partner_required/i18n/zh_TW.po
odoo/addons/account_partner_required/models/__init__.py
odoo/addons/account_partner_required/models/account.py
odoo/addons/account_partner_required/readme/CONFIGURE.rst
odoo/addons/account_partner_required/readme/CONTRIBUTORS.rst
odoo12_addon_account_partner_required-12.0.1.0.0.99.dev13.dist-info/METADATA
odoo12_addon_account_partner_required-12.0.1.0.0.99.dev13.dist-info/WHEEL
odoo12_addon_account_partner_required-12.0.1.0.0.99.dev13.dist-info/top_level.txt
odoo12_addon_account_partner_required-12.0.1.0.0.99.dev13.dist-info/RECORD
